LICENSE
README.md
fixie_sdk/__init__.py
fixie_sdk/examples/voice_example.py
fixie_sdk/voice/__init__.py
fixie_sdk/voice/audio_base.py
fixie_sdk/voice/audio_local.py
fixie_sdk/voice/audio_track.py
fixie_sdk/voice/session.py
fixie_sdk/voice/types.py
fixie_sdk/voice/types_test.py
fixie-0.0.7.dist-info/LICENSE
fixie-0.0.7.dist-info/METADATA
fixie-0.0.7.dist-info/WHEEL
fixie-0.0.7.dist-info/RECORD
