Metadata-Version: 2.1
Name: fixie
Version: 0.0.7
Summary: Fixie.ai SDK for Python. Enables you to build AI-powered voice applications.
Home-page: https://github.com/fixie-ai/fixie-sdk-python
License: MIT
Keywords: fixie,fixie.ai,voice,ai
Author: Fixie.ai Team
Author-email: hello@fixie.ai
Requires-Python: >=3.11,<4.0
Classifier: License :: OSI Approved :: MIT License
Classifier: Programming Language :: Python :: 3
Classifier: Programming Language :: Python :: 3.11
Classifier: Programming Language :: Python :: 3.12
Requires-Dist: dataclasses-json (>=0.6.2,<0.7.0)
Requires-Dist: livekit (==0.7.0.dev1)
Requires-Dist: numpy (>=1.26.2,<2.0.0)
Requires-Dist: pydub (>=0.25.1,<0.26.0)
Requires-Dist: pyee (>=11.1.0,<12.0.0)
Requires-Dist: setuptools (>=69.0.2,<70.0.0)
Requires-Dist: sounddevice (>=0.4.6,<0.5.0)
Requires-Dist: websockets (>=12.0,<13.0)
Project-URL: Repository, https://github.com/fixie-ai/fixie-sdk-python
